dcf_process_assignments/__init__.py
dcf_process_assignments/process_assignments.py
dcf_process_assignments-0.0.0.dist-info/LICENSE
dcf_process_assignments-0.0.0.dist-info/METADATA
dcf_process_assignments-0.0.0.dist-info/WHEEL
dcf_process_assignments-0.0.0.dist-info/entry_points.txt
dcf_process_assignments-0.0.0.dist-info/top_level.txt
dcf_process_assignments-0.0.0.dist-info/RECORD
