Metadata-Version: 2.1
Name: dcf-process-assignments
Version: 0.0.0
Summary: Package to automate processing DCF ThankView Assignments
Home-page: https://github.com/mubbie/dcf-thankview/tree/main/dev/dcf_process_assignments
Author: Mubarak Idoko
Author-email: midoko.dev@gmail.com
License: MIT
Keywords: DCF,ThankView Assignments Processing,Automation
Platform: UNKNOWN
Classifier: Programming Language :: Python :: 3
Classifier: License :: OSI Approved :: MIT License
Classifier: Operating System :: OS Independent
Classifier: Topic :: Software Development :: Libraries :: Python Modules
Requires-Python: >=3.6
License-File: LICENSE
Requires-Dist: pandas
Requires-Dist: argparse
Requires-Dist: setuptools
Requires-Dist: openpyxl
